git_archiver/__init__.py
git_archiver/__main__.py
git_archiver/archive.py
git_archiver/cli.py
git_archiver/discovery.py
git_archiver/exceptions.py
git_archiver/meta.py
git_archiver-0.1.1.dist-info/LICENSE.txt
git_archiver-0.1.1.dist-info/METADATA
git_archiver-0.1.1.dist-info/WHEEL
git_archiver-0.1.1.dist-info/entry_points.txt
git_archiver-0.1.1.dist-info/top_level.txt
git_archiver-0.1.1.dist-info/RECORD
