Metadata-Version: 2.1
Name: git-archiver
Version: 0.1.1
Summary: A tool for mass archiving git repositories
Keywords: git,scm,archive
Classifier: Development Status :: 3 - Alpha
Classifier: Programming Language :: Python :: 3
Classifier: Programming Language :: Python :: 3.10
Classifier: Operating System :: OS Independent
Classifier: License :: OSI Approved :: Apache Software License
Classifier: Framework :: AsyncIO
Classifier: Environment :: Console
Classifier: Topic :: System :: Archiving
Classifier: Topic :: Software Development :: Version Control :: Git
Classifier: Intended Audience :: System Administrators
Requires-Python: >=3.10
License-File: LICENSE.txt
Requires-Dist: git-interface (==0.9.3)
Requires-Dist: aiofiles (~=22.1.0)
